[
    {
        "name": "Alice",
        "gender": "Girl"
    },
    {
        "name": "Alan",
        "gender": "Boy"
    },
    {
        "name": "Andrew",
        "gender": "Boy"
    },
    {
        "name": "Bob",
        "gender": "Boy"
    },
    {
        "name": "Bella",
        "gender": "Girl"
    },
    {
        "name": "Ben",
        "gender": "Boy"
    },
    {
        "name": "Charlie",
        "gender": "Unisex"
    },
    {
        "name": "Chloe",
        "gender": "Girl"
    },
    {
        "name": "Chris",
        "gender": "Unisex"
    },
    {
        "name": "David",
        "gender": "Boy"
    },
    {
        "name": "Daisy",
        "gender": "Girl"
    },
    {
        "name": "Daniel",
        "gender": "Boy"
    },
    {
        "name": "Emma",
        "gender": "Girl"
    },
    {
        "name": "Ethan",
        "gender": "Boy"
    },
    {
        "name": "Edward",
        "gender": "Boy"
    },
    {
        "name": "Fiona",
        "gender": "Girl"
    },
    {
        "name": "Frank",
        "gender": "Boy"
    },
    {
        "name": "Felix",
        "gender": "Boy"
    },
    {
        "name": "Grace",
        "gender": "Girl"
    },
    {
        "name": "George",
        "gender": "Boy"
    },
    {
        "name": "Gabriel",
        "gender": "Unisex"
    },
    {
        "name": "Harry",
        "gender": "Boy"
    },
    {
        "name": "Hannah",
        "gender": "Girl"
    },
    {
        "name": "Helen",
        "gender": "Girl"
    },
    {
        "name": "Isaac",
        "gender": "Boy"
    },
    {
        "name": "Ivy",
        "gender": "Girl"
    },
    {
        "name": "Ian",
        "gender": "Boy"
    },
    {
        "name": "Jack",
        "gender": "Boy"
    },
    {
        "name": "Julia",
        "gender": "Girl"
    },
    {
        "name": "James",
        "gender": "Boy"
    },
    {
        "name": "Kate",
        "gender": "Girl"
    },
    {
        "name": "Kevin",
        "gender": "Boy"
    },
    {
        "name": "Kyle",
        "gender": "Boy"
    },
    {
        "name": "Lucy",
        "gender": "Girl"
    },
    {
        "name": "Liam",
        "gender": "Boy"
    },
    {
        "name": "Leo",
        "gender": "Boy"
    },
    {
        "name": "Mary",
        "gender": "Girl"
    },
    {
        "name": "Michael",
        "gender": "Boy"
    },
    {
        "name": "Mia",
        "gender": "Girl"
    },
    {
        "name": "Noah",
        "gender": "Boy"
    },
    {
        "name": "Nora",
        "gender": "Girl"
    },
    {
        "name": "Nathan",
        "gender": "Boy"
    },
    {
        "name": "Olivia",
        "gender": "Girl"
    },
    {
        "name": "Oscar",
        "gender": "Boy"
    },
    {
        "name": "Owen",
        "gender": "Boy"
    },
    {
        "name": "Paul",
        "gender": "Boy"
    },
    {
        "name": "Penny",
        "gender": "Girl"
    },
    {
        "name": "Peter",
        "gender": "Boy"
    },
    {
        "name": "Quinn",
        "gender": "Unisex"
    },
    {
        "name": "Quincy",
        "gender": "Boy"
    },
    {
        "name": "Ruby",
        "gender": "Girl"
    },
    {
        "name": "Ryan",
        "gender": "Unisex"
    },
    {
        "name": "Rachel",
        "gender": "Girl"
    },
    {
        "name": "Sarah",
        "gender": "Girl"
    },
    {
        "name": "Sam",
        "gender": "Unisex"
    },
    {
        "name": "Sophia",
        "gender": "Girl"
    },
    {
        "name": "Tom",
        "gender": "Boy"
    },
    {
        "name": "Tina",
        "gender": "Girl"
    },
    {
        "name": "Theo",
        "gender": "Boy"
    },
    {
        "name": "Uma",
        "gender": "Girl"
    },
    {
        "name": "Ulysses",
        "gender": "Boy"
    },
    {
        "name": "Victor",
        "gender": "Boy"
    },
    {
        "name": "Violet",
        "gender": "Girl"
    },
    {
        "name": "Vanessa",
        "gender": "Girl"
    },
    {
        "name": "William",
        "gender": "Boy"
    },
    {
        "name": "Wendy",
        "gender": "Girl"
    },
    {
        "name": "Walter",
        "gender": "Boy"
    },
    {
        "name": "Xavier",
        "gender": "Boy"
    },
    {
        "name": "Yolanda",
        "gender": "Girl"
    },
    {
        "name": "Yvonne",
        "gender": "Girl"
    },
    {
        "name": "Zoe",
        "gender": "Girl"
    },
    {
        "name": "Zachary",
        "gender": "Boy"
    }
]